MANIFEST.in
README.rst
description.rst
setup.cfg
setup.py
include/proton/buffer.h
include/proton/cid.h
include/proton/codec.h
include/proton/condition.h
include/proton/connection.h
include/proton/container.h
include/proton/cproton.i
include/proton/delivery.h
include/proton/disposition.h
include/proton/driver.h
include/proton/driver_extras.h
include/proton/engine.h
include/proton/error.h
include/proton/event.h
include/proton/framing.h
include/proton/import_export.h
include/proton/io.h
include/proton/link.h
include/proton/message.h
include/proton/messenger.h
include/proton/object.h
include/proton/parser.h
include/proton/sasl.h
include/proton/scanner.h
include/proton/selectable.h
include/proton/selector.h
include/proton/session.h
include/proton/ssl.h
include/proton/terminus.h
include/proton/transport.h
include/proton/type_compat.h
include/proton/types.h
include/proton/url.h
include/proton/version.h
mqlight/__init__.py
mqlight/cproton.c
mqlight/cproton.cxx
mqlight/cproton.py
mqlight/libqpid-proton.2.0.0.dylib
mqlight/libqpid-proton.dylib
mqlight/libqpid-proton.so
mqlight/libqpid-proton.so.2
mqlight/mqlight.py
mqlight/mqlightexceptions.py
mqlight/mqlightlog.py
mqlight/mqlightproton.py
mqlight/proton.py
mqlight/qpid-proton.dll
mqlight/qpid-proton.lib
mqlight/stubproton.py
mqlight.egg-info/PKG-INFO
mqlight.egg-info/SOURCES.txt
mqlight.egg-info/dependency_links.txt
mqlight.egg-info/top_level.txt
mqlight.egg-info/zip-safe
mqlight/licenses/LA_cs
mqlight/licenses/LA_de
mqlight/licenses/LA_el
mqlight/licenses/LA_en
mqlight/licenses/LA_es
mqlight/licenses/LA_fr
mqlight/licenses/LA_in
mqlight/licenses/LA_it
mqlight/licenses/LA_ja
mqlight/licenses/LA_ko
mqlight/licenses/LA_lt
mqlight/licenses/LA_pl
mqlight/licenses/LA_pt
mqlight/licenses/LA_ru
mqlight/licenses/LA_sl
mqlight/licenses/LA_tr
mqlight/licenses/LA_zh
mqlight/licenses/LA_zh_TW
mqlight/licenses/LI_cs
mqlight/licenses/LI_de
mqlight/licenses/LI_el
mqlight/licenses/LI_en
mqlight/licenses/LI_es
mqlight/licenses/LI_fr
mqlight/licenses/LI_in
mqlight/licenses/LI_it
mqlight/licenses/LI_ja
mqlight/licenses/LI_ko
mqlight/licenses/LI_lt
mqlight/licenses/LI_pl
