Metadata-Version: 1.1
Name: mqlight
Version: 1.0.2015020201b1
Summary: IBM MQ Light Client Python Module
Home-page: https://developer.ibm.com/messaging/mq-light/
Author: IBM
Author-email:  
License: proprietary
Keywords: ibm mqlight
Platform: UNKNOWN
Classifier: Development Status :: 4 - Beta
Classifier: Intended Audience :: Developers
Classifier: Topic :: Software Development
Classifier: Topic :: Communications
Classifier: Topic :: System :: Networking
Classifier: Topic :: Software Development :: Libraries :: Python Modules
Classifier: License :: Other/Proprietary License
Classifier: Operating System :: OS Independent
Classifier: Programming Language :: Python :: 2
Classifier: Programming Language :: Python :: 2.7
